Metadata-Version: 1.0
Name: python-knowledge
Version: 0.0
Summary: knowledge about python for students
Home-page: UNKNOWN
Author: UNKNOWN
Author-email: bloodruslan@gmail.com
License: UNKNOWN
Platform: UNKNOWN
